topsis_Khushi_102053024/__init__.py
topsis_Khushi_102053024/topsis_Khushi_102053024.py
topsis_Khushi_102053024-0.0.1.dist-info/METADATA
topsis_Khushi_102053024-0.0.1.dist-info/WHEEL
topsis_Khushi_102053024-0.0.1.dist-info/top_level.txt
topsis_Khushi_102053024-0.0.1.dist-info/RECORD
