Metadata-Version: 2.1
Name: topsis-Khushi-102053024
Version: 0.0.1
Summary: Topsis package
Author: Khushi Bathla
Author-email: <bathla068@gmail.com>
Keywords: python,topsis,machinelearning,datascience
Classifier: Development Status :: 1 - Planning
Classifier: Intended Audience :: Developers
Classifier: Programming Language :: Python :: 3
Classifier: Operating System :: Unix
Classifier: Operating System :: MacOS :: MacOS X
Classifier: Operating System :: Microsoft :: Windows
Requires-Dist: numpy
Requires-Dist: pandas
